<?xml version="1.0" ?>
<PyBrain>
	<Network class="pybrain.structure.networks.feedforward.FeedForwardNetwork" name="FeedForwardNetwork-188">
		<name val="'FeedForwardNetwork-188'"/>
		<Modules>
			<LinearLayer class="pybrain.structure.modules.linearlayer.LinearLayer" inmodule="True" name="in">
				<dim val="30"/>
				<name val="'in'"/>
			</LinearLayer>
			<LinearLayer class="pybrain.structure.modules.linearlayer.LinearLayer" name="out" outmodule="True">
				<dim val="1"/>
				<name val="'out'"/>
			</LinearLayer>
			<BiasUnit class="pybrain.structure.modules.biasunit.BiasUnit" name="bias">
				<name val="'bias'"/>
			</BiasUnit>
			<SigmoidLayer class="pybrain.structure.modules.sigmoidlayer.SigmoidLayer" name="hidden0">
				<dim val="5"/>
				<name val="'hidden0'"/>
			</SigmoidLayer>
		</Modules>
		<Connections>
			<FullConnection class="pybrain.structure.connections.full.FullConnection" name="FullConnection-185">
				<inmod val="bias"/>
				<outmod val="out"/>
				<Parameters>[-0.45307720112090322]</Parameters>
			</FullConnection>
			<FullConnection class="pybrain.structure.connections.full.FullConnection" name="FullConnection-186">
				<inmod val="bias"/>
				<outmod val="hidden0"/>
				<Parameters>[0.0086581680781058507, 2.0792998942795049, -1.0774174220105681, -0.091259812694293091, -1.5350995458474668]</Parameters>
			</FullConnection>
			<FullConnection class="pybrain.structure.connections.full.FullConnection" name="FullConnection-187">
				<inmod val="in"/>
				<outmod val="hidden0"/>
				<Parameters>[1.3839508544540762, -0.56754561959526584, -0.49683271877133811, -2.2213080101804441, -0.50679719631458942, -0.16448957732499175, -0.38702328386103063, 0.53773050532841715, -1.2978616360703048, 1.6166663757030058, 1.290336584311913, 0.42069454520178462, -2.1056948666139963, 0.11398885375653256, -0.52902248315987555, -0.62763421755329063, -0.18654147924397871, -0.83849980797763091, -0.64017710825065077, 0.55782129347226983, -1.0739339805062502, 0.52132678075647243, -1.3482497441619854, -0.10276353967875822, 0.6373553691074263, 0.75515736281077483, 1.8034189191110326, -1.9401524510213557, -0.45247879255994822, 1.5644705301179358, 0.87912594170193215, -1.0045895258057096, -0.66964701875441723, -0.88627136222895508, -1.581116242324595, 1.1585162235356072, 0.7039926742875926, 0.0051824976172577045, 1.2758965936843989, -0.39832893153522297, -0.4755506898905858, 2.3695310719464415, 2.5291178922095452, 0.66419115874671109, 0.72023396172310339, 0.75002550824950565, -0.2421387988796721, 1.5357812558469399, -1.9223082206489075, 0.79281713895752071, 1.6255810829388135, -0.2116689996410086, 1.7471726982084521, 1.5077065836249308, 0.50116272517054983, -0.37915350016580501, 0.82841483188315179, 0.36867813186093168, -0.36992311362207603, 0.49442406964155383, 0.54208739407885798, -0.46801857447281325, -3.0304615101247214, -0.61732985747096092, -0.05639337208349663, 1.6428200565002038, -0.27476854395127165, -1.0321184817346416, -0.82358880187607098, 1.6072975012693702, -1.1643660284349897, -0.42851015116406349, 0.82121993314306563, 1.4367042938912116, 2.393927115413073, 0.37059289542157903, 1.6664451874044541, -0.35744693303071634, 1.1618579781424612, 0.11128060277668761, 0.098469203499644706, 0.77792405773009055, 2.0673184900845047, 0.055680916321712966, -0.37566124887219648, 2.1964298515596918, -0.85351545481725899, -1.1414659383221804, 0.043810979359383086, -1.8443141114980095, 0.82722789678273745, 0.099650142744538914, -2.5084577181811683, 0.66840204033079775, 0.64026319362562822, 0.67177479468998047, -1.0255895602361256, -2.1296124970264594, -0.90274720010202036, 0.55818849912677737, -0.74715026414529662, -0.78328154171361775, 0.68457238938913878, -1.1553527118622497, 0.45561325800414842, 0.91780729925564186, 0.14914898615593064, 2.3989111748168734, -0.47098515855236855, 1.0209915139446106, -0.16293700026091218, 0.42447975038571084, -0.34242581586423537, 0.39900535728931341, 1.0372019502360394, -0.025771131022826833, 0.78636672509220507, -1.2042312934105166, -1.0507716579699673, 0.27672799565847706, 1.0883693282529034, -0.54511764486980097, -0.89206894079488186, 0.0058413385409652359, 0.49801320383421421, 1.1443306713055332, 1.0743227311856551, -0.24630227644518543, 0.3307991889079453, -0.058588203608271799, 1.0215205173010469, 1.4877087138069665, -0.30090019506521426, 0.70860755049894009, 1.5769846548370323, 0.48338602030551669, 0.070286523835135006, 0.80520408254383524, 1.2826794224778326, -1.1838452734311138, 0.10884147570790143, -0.91798289122611532, 0.68905200334193228, -0.10662113347671559, 0.68918219068264774, 0.85504409285936467, -0.2871420552743052, 1.4193864611477625, -0.48223179790918586, 0.61739332153353244]</Parameters>
			</FullConnection>
			<FullConnection class="pybrain.structure.connections.full.FullConnection" name="FullConnection-184">
				<inmod val="hidden0"/>
				<outmod val="out"/>
				<Parameters>[0.33949000672776597, 0.34392496533162248, -0.19329355438029869, -0.022749914059486086, 0.52254412133809214]</Parameters>
			</FullConnection>
		</Connections>
	</Network>
</PyBrain>
