<?xml version="1.0" ?>
<PyBrain>
	<Network class="pybrain.structure.networks.recurrent.RecurrentNetwork" name="RecurrentNetwork-239">
		<name val="'RecurrentNetwork-239'"/>
		<Modules>
			<LinearLayer class="pybrain.structure.modules.linearlayer.LinearLayer" inmodule="True" name="in">
				<dim val="30"/>
				<name val="'in'"/>
			</LinearLayer>
			<LinearLayer class="pybrain.structure.modules.linearlayer.LinearLayer" name="out" outmodule="True">
				<dim val="1"/>
				<name val="'out'"/>
			</LinearLayer>
			<LinearLayer class="pybrain.structure.modules.linearlayer.LinearLayer" name="context">
				<dim val="5"/>
				<name val="'context'"/>
			</LinearLayer>
			<SigmoidLayer class="pybrain.structure.modules.sigmoidlayer.SigmoidLayer" name="hidden">
				<dim val="5"/>
				<name val="'hidden'"/>
			</SigmoidLayer>
		</Modules>
		<Connections>
			<FullConnection class="pybrain.structure.connections.full.FullConnection" name="in_to_hidden">
				<inmod val="in"/>
				<outmod val="hidden"/>
				<Parameters>[0.22779472810606405, -1.6358817236694276, -0.096363218783351981, 0.11071354072854983, 1.896805103767635, 1.0935390892288013, -0.42218120023021927, -0.19597893847580422, -0.95165984046172769, -0.5365830085880563, 0.03469445130729247, 1.3520755849096409, -0.73434773584049551, -0.39480994828393356, -1.1253928434929097, 0.063945430165086942, -0.78349545358472961, 0.31919557654777364, -0.43153050763388107, 0.38116810001728357, 1.2077472977624066, 1.339460899404419, -0.12667522443944296, 0.038045558438111665, 1.1120479069975333, -1.7377136971596046, 0.6098346936646486, 0.38866727438576548, 0.59714801964529318, -0.53287035706645303, -0.29181216996643083, -0.28402877937809201, 2.1655916869627925, 2.0233439955657464, -0.91865919310623489, -0.61074670715278079, 0.067607963639062199, 0.1676146019039525, 0.18311600540472225, -0.28010966390835312, -0.20694805869954824, 1.3407708183466975, -1.2487458229751125, -0.34351744437900256, -0.58533039394685316, 0.21666627488029117, -0.54468234155297979, -2.0084900840312923, 1.122499846400919, -1.7691777802215027, -0.86271499348003533, 1.8065463449063381, -0.22150469639815515, 0.55806367560835379, -0.43234701982774104, 0.29646487658509463, 0.7517291735986994, -0.9560670085416515, -0.33768756446436771, 0.48067360889987409, 0.61928575362227212, 1.076737210878304, -2.7024542362097774, 1.3294302345287294, 0.94172904605616603, 0.20524610974994337, -2.554772507122133, -1.8082690201308924, 1.5854699450474647, -0.094573288298369002, -1.3143361152746964, -0.70029333315030551, -1.016534771734374, -0.78756747794717075, 0.88591679476924512, 1.6312048571945668, 1.1274029870187672, -0.015778910060401424, -1.7468568097242563, -1.7274932188778371, 0.67532232288749194, -0.17681161685048874, -0.12643912673551291, 0.025743015462547803, 0.14294399279274608, -0.17059694299493994, 0.87887914046989579, -0.48614321577989744, -0.30348955462824756, -0.45854508697228119, 0.22097441254662725, 2.1502215068441175, -1.3854407678440495, -0.4791212217995483, 0.40519820089500896, 1.4906633968616747, 0.48745225533693254, 0.21472134301441737, -0.72455780982904672, 0.35898454480957892, -0.097027501851856143, 0.41854112925122117, 0.29694728808190574, -0.44560246883483412, -1.0015962734570603, -0.15833499096411197, 0.36161571694861544, 0.67939477821089089, -0.089983684697100469, -1.3407826728633543, -0.33547557051013882, 0.84375264627428237, -0.34906105307272184, 1.0933536429894579, -0.28989222621429289, 0.20834023024063483, -1.3814494950557719, 0.58047789200783373, 0.32743278359381456, 0.64817240560881162, -0.013703820348379652, 0.21001106283217252, 0.54181301045195229, 1.8461309183807153, 1.3866819872376881, -0.23504170855118642, -0.31235744632446388, -0.71553823062233313, -0.98447872281126081, -1.4592992693368381, -0.20891888971656408, -0.22575326518594813, 0.56421775187377532, 1.5429889486721959, -0.26109048529952322, -0.028441189724393485, -1.9549097984245161, 0.52769873469042194, 0.51014039267766254, -0.042814808853741469, 0.41929942221457883, 0.57197899050499423, 1.2443724570267591, -1.3491972646893833, 0.30779542269090998, 0.26071717925157206, 0.53157202157330752, 1.0182953809860522, -1.5247162889016572, 0.81614887433851713]</Parameters>
			</FullConnection>
			<FullConnection class="pybrain.structure.connections.full.FullConnection" name="hidden_to_out">
				<inmod val="hidden"/>
				<outmod val="out"/>
				<Parameters>[-0.14458285080628872, 0.040469004550340595, 0.015617788583350965, 0.30618788921216111, 0.11559536360666142]</Parameters>
			</FullConnection>
			<FullConnection class="pybrain.structure.connections.full.FullConnection" name="FullConnection-238" recurrent="True">
				<inmod val="hidden"/>
				<outmod val="context"/>
				<Parameters>[-0.15444551351269076, -0.28913554360729027, 0.086749920796119345, -0.4572343851131182, -0.22568683321781494, -0.5089959918936352, -1.220853290051249, 0.17508912603098675, 2.4868348540876304, -0.12983684689478112, -0.44220302408895756, 0.029132563266031836, 0.60284041404926325, 0.79872969461367882, -1.3531724397178386, -0.37777499548918347, -0.35474177300118442, -0.4875845052986999, 0.56071572961661953, 1.5605606433602652, 2.0706080931287767, -0.64514184435245758, -1.1708947635852949, 2.3162805550637926, 0.033907176008050766]</Parameters>
			</FullConnection>
		</Connections>
	</Network>
</PyBrain>
