<?xml version="1.0" ?>
<PyBrain>
	<Network class="pybrain.structure.networks.recurrent.RecurrentNetwork" name="RecurrentNetwork-143">
		<name val="'RecurrentNetwork-143'"/>
		<Modules>
			<LinearLayer class="pybrain.structure.modules.linearlayer.LinearLayer" inmodule="True" name="in">
				<dim val="30"/>
				<name val="'in'"/>
			</LinearLayer>
			<LinearLayer class="pybrain.structure.modules.linearlayer.LinearLayer" name="out" outmodule="True">
				<dim val="1"/>
				<name val="'out'"/>
			</LinearLayer>
			<LinearLayer class="pybrain.structure.modules.linearlayer.LinearLayer" name="context">
				<dim val="11"/>
				<name val="'context'"/>
			</LinearLayer>
			<TanhLayer class="pybrain.structure.modules.tanhlayer.TanhLayer" name="hidden">
				<dim val="11"/>
				<name val="'hidden'"/>
			</TanhLayer>
		</Modules>
		<Connections>
			<FullConnection class="pybrain.structure.connections.full.FullConnection" name="in_to_hidden">
				<inmod val="in"/>
				<outmod val="hidden"/>
				<Parameters>[-0.20020755679559782, 0.021574090705355996, -0.67229849047113099, -0.90764755311271494, 0.11184219126250849, -1.5524264883981902, 1.4307039734074625, -0.98432773415694297, -0.55120300229998187, 0.033704627029388833, -0.050067768115929286, 0.23426362017145408, 0.24920801849039775, -0.95198564049300971, 0.49630634829307996, 1.0741741776174163, 0.26892738382145415, 1.5787590066330266, 0.69108978646024111, 0.75922488323173576, -1.4766211900600519, -0.66520080174643026, 0.62975599483806866, 0.12653998396551625, 0.55107254343927736, -1.6834221867770109, 0.62741724031629786, -0.3677241946707866, 1.3808602478427627, -0.93165715840959573, 1.4113696286303394, 0.39282227148569887, -0.35954182999755119, -0.32318220046083229, 1.4294432968704092, -0.28354966514940116, 0.13198190230496859, 1.2262920904294787, 0.67207180449540949, 1.7998747717680448, -0.32407673043359869, -0.94319208155080869, 0.053952953950917114, 0.35367686807106363, 1.2659426668287497, 0.11038814362289523, 0.1830237365915694, 0.62818070269764203, 0.4014199734168587, 0.13976362027568301, -1.4626988659160274, -0.33277657061543392, 0.43387629378410042, 0.53376621163586235, -0.45244540647157172, 0.0061624124278354033, 0.33384018821074574, 1.8575427256375441, 0.21429956047200832, -0.24792224370096366, 0.036279855663520426, 0.93038914236893822, -0.88023825665485622, 1.7682099172082959, 0.29270200573754529, -0.092649050059028223, -0.35415230323301855, 1.6461703664723666, -0.064256578853438925, 1.3450195267243386, 0.9407363357629499, -0.48568353261298991, 0.10942913228307863, -0.50477699422429045, 0.35854701586952564, 0.0056448152197691327, -0.66657077545334131, 0.42915609119700715, -0.88028527625072295, -0.28464309428095624, 1.2786072027392532, 0.28245224892358234, -2.2717074709223311, 0.30368151960503259, 0.52141236275068603, 1.5258316337422633, -1.0573428153376012, 1.0473139901056321, 0.88550799225616239, 0.32295750302067455, -1.2340005732118122, 2.1620679003989145, -0.013442494984450612, 0.5915274666294188, -0.56420115029313189, -0.68803996907476672, 0.22536474812764934, -1.2084907271019796, -1.1323568632926779, 0.73816656150024129, 0.98480381634166059, -0.32518781574834227, -2.2917789676839302, 2.0772091704843256, 1.0855883513516809, -1.2923226258632923, 0.091657320399303924, 0.76916283034013688, -0.73433246440340949, -0.5832403937583478, 0.70457921413194657, -0.33228490172874703, -2.0886112099546037, 1.4918451983029246, -0.36531972247510341, 0.051274812257399528, 0.23043033189204876, 0.22054091604341494, -0.036509302760356736, 2.1356010239339671, 1.2856584474179982, 1.7762255246690031, 0.6336039101159181, 0.043527316913632576, -0.88596012350728348, -0.17975463969026026, 0.37319403693757158, -0.062357383439164818, -1.0205615374635217, -0.44451996621293344, 0.66384497123838104, 0.26905724791394869, -0.35491770563237346, 1.4352382651818321, 0.14026458963387789, 1.084515528363909, -0.53584955964908243, 0.36971100366260223, -0.46826004410888195, 0.001706325217091809, 0.40700688969342658, -0.96538061626646676, 0.15044895794555979, -1.1720550612375804, 1.0341804084641235, -0.45029495222312582, -0.97797852753927328, 1.1943587671494307, 0.064701238342748088, -0.32979762173836547, -1.3581785955945398, 0.2946318124117579, 1.7332735012347618, 1.8933870777588688, -0.23460155390743684, 1.3060517680539836, -0.072423769590145695, -0.26719645978083911, -1.8853864314330135, -0.51865134608178765, 1.2208712431242685, -1.7750516049079619, -1.6512828113495566, 0.61497059884294825, -1.4405667051987319, -0.7465006375610016, -1.6259853927247685, 0.86413161632952806, -0.3039339638572674, 0.52080424376505785, -0.021204825583671393, -0.66027867937714646, 1.3205132687959173, -1.0899329655048713, -0.12822565398272587, -0.084242484206631607, -1.8258430289648018, -0.41832070990287751, -0.32189485284075381, 0.72384204804964847, -1.2362805789109017, 0.30718977196087299, 0.45963300710459815, -0.70081262644367237, -0.98513811260565509, -0.56524239253057162, 0.96278650403049437, -0.99786123705068586, -0.56312438329594228, 1.9744560239698361, -1.0300792225629298, -0.80131309612997315, 0.54201687042166258, 0.76222405327181086, -0.087784152010363353, 0.35216351379047695, -0.63947289756785242, 0.55033900997079699, 0.0046951704254864718, 0.23403441368407391, 0.18565757585167744, -1.3772133302096812, 0.02695005033155826, 0.11508959054477089, -1.0096955399021041, 1.449227276524816, -0.18657834221455633, -1.1998913854279685, 0.75952864556505384, -0.48766195886880775, -1.0302417979025964, 1.151268053820603, -0.91284838583421313, 0.96250408948269783, -0.41295549337068133, 1.1391471319633941, 0.63949024907597929, 1.9842203182220031, -0.062355713221552075, 0.716406330094841, -0.63280444405035507, 1.2149986054369759, 0.87847030230784762, -0.38201741954407675, -0.66738656017583187, -1.3121570963368259, 1.0103405093977922, -0.77869587807360441, -1.7751926706740575, -0.65236800256567817, 0.81728775160608846, 0.33406657629386111, -1.2517532281998489, -0.040121646674294735, 0.3427400631992385, -0.84710675194275953, -1.2460226952735121, -0.91382051859130686, -0.26284462980251272, -0.7323528955760118, 0.21776390750661992, 0.80414775731594357, 0.32811645233689796, -0.21081801369798858, 1.2898032343203623, 1.4508773774102093, -0.57496221429285377, -0.51875483773945885, -0.42846014558862144, -2.6270881641950341, -0.21731228081841475, -0.90332775715944047, -1.113611485066506, 0.4547634854186608, 1.2554239641840852, -0.58235631446207481, -1.1320801051330711, -0.49170481802148747, 1.8552932843160592, -1.3392239140776387, -1.7000773985977899, -0.2341604602962615, -0.11857022874646013, 0.75903243031541712, -1.025405407048978, -1.5769767884315931, -1.2871111273829947, -1.2187532120528308, 2.1510044280037448, -1.4970662977459168, 1.2808209668008468, -0.16108128344924261, 0.071876911675721314, 1.0009259004238407, -0.15468687574608231, -0.11688107963073971, -0.58800020872623449, -0.43387497243789375, -0.1003787575181715, 0.8191058635161379, 0.67916509316826823, 1.294655970861126, 1.4242895702328437, -0.3607117584879922, -0.5552331614407352, 0.89727345411081083, -0.58086408665281331, 0.00087326108810600064, -0.57348228722811889, -0.55297292170793189, 2.602348866120292, 0.67774653933994633, 1.1416253826057123, -1.538101423110031, 0.4323474596075465, 0.65166049048962693, -0.7706134986403429, 0.40494547931694641, -1.6346370547381772, -0.41509233046159094, 0.8855202864603019, 1.8010061289172079, 0.89319761954337462, 1.5638429129661251, 1.1087094691701775, -0.63022982900129232, -0.03292016555068162, -0.96261986899604968, 1.5962826969396313, 0.32192179676860366, 0.1561592338208343, 0.85744815621270265, 0.8769949586976723, -0.38149145415013636, -0.42997670923512482, -0.68541822681410314, 0.53041132970019456, 0.88387576454091576, 1.083266772822058, -1.1396422474325643, -0.57194019544650898, 0.66880206877838544, 1.2945665661515335, 0.49118073490727282, -1.084137474936592, -2.6658942705248769, 0.042224953239955995, 1.2385208530815546, 1.4041646437611859, 0.19340586520041614]</Parameters>
			</FullConnection>
			<FullConnection class="pybrain.structure.connections.full.FullConnection" name="hidden_to_out">
				<inmod val="hidden"/>
				<outmod val="out"/>
				<Parameters>[-0.067363532543800148, -0.52522574465427163, 0.18998022189294969, -0.080318247525419398, 0.089029499253478181, -0.047905584149132832, 0.024619923371240311, -0.093146080242274693, -0.25540451232282413, -0.30405826335744929, 0.40283512856659542]</Parameters>
			</FullConnection>
			<FullConnection class="pybrain.structure.connections.full.FullConnection" name="FullConnection-142" recurrent="True">
				<inmod val="hidden"/>
				<outmod val="context"/>
				<Parameters>[0.17076678351706909, -1.2297558371713597, 0.20521062189852263, -1.7606285108294648, 1.9307354874631921, 0.64737684573285381, 1.3191802496356384, 0.5575436934609973, 1.4038541374159987, -1.2879787271323018, -1.4478406725137454, 1.2147804043839274, 1.3179033191832166, -0.87842361512636657, 0.7226406382520445, 1.1089601224546857, 1.6370702848104861, 1.4569016836307289, 0.84615611025491899, 0.41919802967744924, -0.67366832457997283, 0.25396942981679427, -0.22772311752086039, -0.075506019749468203, -1.5352903975430952, -0.8324287393215215, -0.53896535929448164, -0.78466969168655676, -0.19512310463914614, -0.40243931433494784, 0.20137709994271705, 0.16914611243197539, 0.35725772592666333, 1.3854345505475265, -0.27757904387793353, -1.2704540305576779, -1.5254953067396329, -0.23413101956911808, -1.008866009506256, 0.59072640863603632, -0.75621079880866571, -0.14970802965650146, 0.37880284061007535, 0.023917169706255362, -1.7084816634560136, 1.5864473648429505, -1.6919639088463143, 0.38931622374294861, 0.40622262608689352, 0.14062381501217511, 0.58985388366632041, 0.87365480650630933, -0.20311449233186218, 0.73923224108678287, -2.3283948158496033, -0.62690731330385419, -1.0177621255692975, -0.64577057553412154, 0.31752177354823558, 0.68925503647844222, 0.18522710861063296, 0.82688271344503572, 0.14827014833433622, 0.99384543766686495, 0.20449488537928506, 0.55980647228815572, -0.15805440318114358, -0.51852574134558949, -0.022132044760789164, -0.40329578292508583, 0.43249450456760674, -1.4263183539685269, 0.75135603832834474, -0.37107976428077016, -0.42263664054164063, -1.7056841763747312, -0.81583525503142351, -0.31780956504770824, 0.52842114909352189, -0.34695889425168813, 2.012447704002212, 0.17973021941817427, 0.2408482703187409, 2.1983590866637179, 1.2083070915099852, -0.25102139304852544, -0.21903218793085419, -0.30118836698840518, 0.011158591185510471, -0.85751952338956738, -0.54179965443916367, -0.10199258589470879, -0.97525109257995901, 0.91802813080659318, 0.52203957806322765, 0.57900053590150113, 0.71161577426742439, 0.43244533389064194, 0.7013929953357928, 0.19875549147394014, 0.44498169305645013, 0.44463913897215873, 1.4121025904773512, 0.2382388304860639, -0.94735317669615149, 1.2555276109784181, 1.2860201344452431, 0.037677116829755962, -0.13139430553156292, -0.76141538693479072, -0.79088320914801813, 0.53070224569952751, -0.61444504056824689, 0.037191483873492873, 0.76070466162808881, -0.7926144404314247, -0.64334269411115763, 0.79262716681237544, 0.59670116544237373, -0.05552334960577935, -0.18022429683277411]</Parameters>
			</FullConnection>
		</Connections>
	</Network>
</PyBrain>
