<?xml version="1.0" ?>
<PyBrain>
	<Network class="pybrain.structure.networks.recurrent.RecurrentNetwork" name="RecurrentNetwork-5">
		<name val="'RecurrentNetwork-5'"/>
		<Modules>
			<LinearLayer class="pybrain.structure.modules.linearlayer.LinearLayer" inmodule="True" name="in">
				<dim val="30"/>
				<name val="'in'"/>
			</LinearLayer>
			<LinearLayer class="pybrain.structure.modules.linearlayer.LinearLayer" name="out" outmodule="True">
				<dim val="1"/>
				<name val="'out'"/>
			</LinearLayer>
			<LinearLayer class="pybrain.structure.modules.linearlayer.LinearLayer" name="context">
				<dim val="8"/>
				<name val="'context'"/>
			</LinearLayer>
			<TanhLayer class="pybrain.structure.modules.tanhlayer.TanhLayer" name="hidden">
				<dim val="8"/>
				<name val="'hidden'"/>
			</TanhLayer>
		</Modules>
		<Connections>
			<FullConnection class="pybrain.structure.connections.full.FullConnection" name="in_to_hidden">
				<inmod val="in"/>
				<outmod val="hidden"/>
				<Parameters>[0.60274813930866578, 1.8989761564716965, 0.20171816249458183, -0.72265066550542545, 0.047956338794599027, -1.8798770491087067, 0.40442392557767248, 0.94131764407410212, 0.32136768099771407, -0.01785250406978664, 1.2067278299901312, 0.17724998920151308, 0.16163411198186237, 1.1517887634288988, -0.07825831660583793, 0.23791724052556745, -1.9078384189548605, 0.78524586856873568, -0.81191480111390002, 1.0999921531753316, 1.6858313952851742, -1.1584103708551843, -2.0641553959199976, -0.47611275906624895, -0.71899801943125508, 0.59160524374960266, 1.6559734582057808, 1.2833149912669133, -0.22773870357569642, 1.2279373415197328, -1.0483831717617107, -1.3953141292921907, 0.6114851852168941, 0.93319431304513034, -0.42982106115677371, 2.4764815608816662, -0.55693808282918966, 0.057324188068327821, -0.78738822512691475, 0.47967468184190065, 0.010477323711036194, 0.82202739033017791, -0.16112465786655936, 0.48758628422671468, -0.95422123960454663, -1.384276875959872, 0.93489174247195217, 1.1398278563748321, 0.40137456614530487, -1.5639821256095674, -0.15104766378414675, -0.33367947368619444, -0.63089114846886807, 0.27211852355295635, 1.4442559921744293, 1.7129511197762297, 1.0486958137193814, 0.36166193988401024, -1.1879382646120917, -0.92493301191668686, -0.095504189899888417, -0.55300963430925798, -0.91082007341907389, 0.53878666085631488, -0.96880044773080198, -1.0739105133995843, -1.0701079983794526, -0.12666052247163911, -1.0044109567253316, 0.0091571997666157305, 0.71134964398776412, -0.56908490988110705, 0.83651037366929137, 0.63519470522360733, -0.55089522882329223, -0.59238719154186892, 2.1732214061772566, -0.015108817983984092, -0.37542996101205212, -0.3176267644082269, -0.31678140059056042, 0.96961524279132139, 0.79725392565439945, 0.059706020635165641, -0.38558971809599069, -1.802686592176107, -0.36278062739885403, -0.091535948077701296, 0.90632242249206885, 0.34127774134244537, 0.73482291091068952, -0.059408123359071217, 1.5177367464106701, 1.601969495326151, -0.35176836194965833, -0.58267035588943372, -1.2786286940028828, -0.66746542143184917, -0.19403470402695153, -0.98875289626443508, 0.19956570016785516, 0.33670102040687788, -2.625138240794068, 0.91684424350501248, -0.33703417559487048, 0.33746935780430209, -0.51484108126415451, -1.0459148636147806, -1.9278082057688644, 0.81146353499528245, -0.21655957464411921, -0.14008703165492881, 1.3122604620956781, 0.16020049789459198, -0.85711242531385401, 0.75342891970346626, 0.082619263861232597, -1.0694989966630952, -1.406973991184733, 0.41393971248454536, -0.18736743081272078, -0.90358243414454731, -0.41832910424181058, -0.057076341213476316, 1.2076178789591125, 0.78806158775362123, 1.2430770963727302, -0.074624509377165416, 1.5673397019351609, -0.67427639388672034, -0.22116498012916905, -2.1550941438146536, -1.1003640142174036, 2.1155340019762927, 0.054764496501728113, 1.1313816829471615, 0.079189322784580241, 0.45817878068471546, 0.86898278107451254, -0.64326756786946371, -1.1973946141578167, 0.30272295584187525, 1.6439676060746025, -0.026685880125604206, -0.390808234183392, 1.8448356058814392, -0.52818549133567927, 0.41367580227629058, -0.48079262646957732, -0.023158218340271076, 2.0540011725771263, -0.202921206017321, 0.071005087363999964, -0.5677928123008158, 0.10195965595928932, 1.2286201331961228, 0.13245271452544843, 0.11624409435755263, 1.0514736301402461, -0.086167499949826643, 1.5260902485177692, -0.071896408747024354, 0.82754848148878823, -0.21419450669180978, -1.1021565049189481, 0.82094482810839342, 0.90388682403185927, -2.108342579693387, -0.51856861429852963, -1.1108772613374311, -0.15192928040341167, 0.33288576578424484, 1.9726964307268047, -0.87582123766777886, -0.16355219244704247, 0.066517599678513173, 0.40498630055882417, -0.027803557037957744, 2.1337880050850906, 0.92810785609441859, -1.6039371384966632, -0.7865354478650427, 0.17800080860903084, -0.74256692097900989, -2.2426147868428257, 1.049114370212187, -0.21642419423481818, 0.41495092487595286, 3.5593672005454016, 0.36686015151960027, -0.60432967831670548, 2.7602575215776515, 0.63441690236673765, -0.8844061736669584, 0.16728098535477581, -0.3701460196520896, -0.48000292041098436, -0.20107860063163246, -1.6715440509483732, -1.137298388557292, -0.49158473826737464, 1.0521022896801133, -0.59200817307990528, -1.2220937946776997, 0.21642695811404519, -0.3482736076002928, 0.021195832473987059, -0.4012313703307418, -0.18432135097493282, -0.77298024627094575, 1.4828667717683377, 0.6488857794617644, -0.87014934087846652, -1.9697631316975088, 0.21056375811061256, -2.2244631861971156, -1.863207625031601, 1.0215158519258125, 1.4440327665723376, 2.4381244889069955, -1.3421848304211679, 0.26697605649508155, 1.8232307068498042, 1.157727265620873, 0.17147529560496028, 0.71341887896128764, -1.7500813093678, -0.16747633736936007, -0.70554843090843067, 0.085063543970031699, -0.56171336245139158, 0.24525938990052698, -1.251352032186025, 0.74119094143845876, -0.4671194686629157, -0.89175976033817772, -0.13459672912780316, -0.517828044859034, 0.22276536635183025, -0.33366470713911234]</Parameters>
			</FullConnection>
			<FullConnection class="pybrain.structure.connections.full.FullConnection" name="hidden_to_out">
				<inmod val="hidden"/>
				<outmod val="out"/>
				<Parameters>[0.11234313651413107, -0.0076690247552172117, 0.078663091637790936, 0.0010438061047748845, 0.030987372993842445, 0.094046037495757698, 0.0043641804213637335, -0.046062342728062068]</Parameters>
			</FullConnection>
			<FullConnection class="pybrain.structure.connections.full.FullConnection" name="FullConnection-4" recurrent="True">
				<inmod val="hidden"/>
				<outmod val="context"/>
				<Parameters>[1.6898239063286733, -0.60850925213369311, -0.21014668943106909, 0.96089939018762216, 1.3135204470423165, -1.36994070559548, -1.545785418294781, 0.6771761580663006, -0.21573500752153144, -1.0366215200967337, -0.53161643676360248, 0.019838647801791114, 0.99280599702965067, -0.35986357900527555, 0.41916595456900396, -0.74412050974844191, -2.0407108024050178, -0.081804015644312125, -1.136603642613891, 1.3956532080614883, 0.73164317610239515, 0.40626524195324487, -1.0340912140457721, 0.34520830040621359, -1.8981845908186812, -0.98139374765179754, -0.77572768111584933, 0.26218354440329344, 0.87424150189495131, -0.55581626320968824, 0.48303558947807346, 1.568174279546678, 0.59917744777055881, 0.95179160979265853, 0.048424481885620395, -0.65135268066309038, 0.64414051366134362, -0.74499791808158777, 1.1273693431900955, 2.5729294614803009, -1.4868989786800317, -0.51350622085035491, 0.057282437756469164, -2.1778024571456207, -0.92714779493737576, 8.5528482153417504e-05, 1.5864166137606361, 0.99635898878358542, 1.1530531789302136, 0.94856042627467807, 0.093537394414506356, -1.1380316388201097, 0.27538858098733232, 0.55660482185514437, 1.5441806260853066, 0.3362240206772803, 1.0783427594162029, -0.086134025865054656, -0.10889761710890532, 2.4387756469559942, -1.2570162861838403, 0.75657695482765697, -0.39795473704274892, 1.2720328017515348]</Parameters>
			</FullConnection>
		</Connections>
	</Network>
</PyBrain>
