<?xml version="1.0" ?>
<PyBrain>
	<Network class="pybrain.structure.networks.recurrent.RecurrentNetwork" name="RecurrentNetwork-17">
		<name val="'RecurrentNetwork-17'"/>
		<Modules>
			<LinearLayer class="pybrain.structure.modules.linearlayer.LinearLayer" inmodule="True" name="in">
				<dim val="30"/>
				<name val="'in'"/>
			</LinearLayer>
			<LinearLayer class="pybrain.structure.modules.linearlayer.LinearLayer" name="out" outmodule="True">
				<dim val="1"/>
				<name val="'out'"/>
			</LinearLayer>
			<LinearLayer class="pybrain.structure.modules.linearlayer.LinearLayer" name="context">
				<dim val="8"/>
				<name val="'context'"/>
			</LinearLayer>
			<TanhLayer class="pybrain.structure.modules.tanhlayer.TanhLayer" name="hidden">
				<dim val="8"/>
				<name val="'hidden'"/>
			</TanhLayer>
		</Modules>
		<Connections>
			<FullConnection class="pybrain.structure.connections.full.FullConnection" name="in_to_hidden">
				<inmod val="in"/>
				<outmod val="hidden"/>
				<Parameters>[0.093933868045536897, 0.82226479544308884, -0.45419254327213238, 1.3625395460152183, 1.7462861571467423, -1.6901276207762546, -0.37806556039043865, 0.63763480584432253, 0.49226295273492027, -1.0082741129631865, 1.4914144389065336, 0.0023791232614066159, 0.36468844428984581, 0.68119666530705703, 0.69689078129675264, -0.14672802162172077, -1.4056218965028922, 0.10001925313495726, 0.50940565989732522, 1.6036141722537087, 0.92512154610371444, 0.075879862533823728, -1.0510126310301635, -0.31516937284601632, 0.90712718531581893, 1.7795505883744376, 0.03847162014817266, 0.96856947862097609, 1.2363472580427184, -0.91312819611831697, -1.2472141951560827, -0.27212304701125978, 0.40296817692731979, -0.38516043041628434, 0.81590259256214381, -0.2769223828177842, 0.60221855225979604, 1.6954987691320209, -1.8617624803733919, 1.8908234128796118, -1.3551952432276568, 0.36543072005784732, -0.066127759384029733, -0.53110224274711271, 0.19660852381085123, -0.68701482980517548, -0.98112665528970455, -1.5239750228000557, -0.80854085066067483, 1.0098370454756793, -0.76185536269070298, 1.3446688644638927, -0.99717201704515812, 0.95915170390769655, -0.43930323768496721, -0.86111722506033783, 0.08634772248157635, 0.60355153723072141, -0.54404601063013125, 0.69355965715047108, -0.19083405401178802, -0.86411309042242568, -0.78930361696898932, 0.086766156624061022, -1.1382772181517189, -1.8284373572359383, 1.3594651366968966, 1.1752620822446274, -0.62986461663419024, 0.031454616504417859, 0.46870070830051958, 1.2340399510540991, -0.16532229082974659, 1.2834161941892417, -0.97703069819684418, 2.630271622096084, -0.057235086744940294, 1.4368644527243446, 0.28332038754551453, -0.014300242331558213, 0.12181503069468048, -0.3529633307948965, -0.9810726838467666, -0.43201487315124926, -0.68836318242860739, 0.033618573489994336, 0.57292220706973906, 1.4553801308125298, -1.1569926182209733, -0.012430459455616043, 0.89815475071384387, 0.78793588767297706, 0.27674396916163529, -1.3265465634936651, -0.45053632038841229, 0.15687580170307133, -0.58122909612832752, -0.85159976345228783, -1.1116494254219675, 0.68549469744635261, 0.9250304162979186, 1.4295771101741148, 0.19813964330443035, -0.71931738452260097, -0.72095734713809445, -0.32079950552076397, -0.59409789664492962, -0.14934266924855702, 0.26586458319847889, -0.09385749253623378, -0.59359037507257706, -0.33161573330757499, 0.71067735701592682, -0.28534025958464831, -1.4566323015082794, -1.0676026166509347, 0.37780159181218015, 0.26240333678629657, 1.1349550388887089, -0.58769748931510613, 0.43496401357225056, 0.051868879454632436, 0.62887388066564565, -0.033933453555031516, -2.1156014957552638, -0.71725044386110071, -0.20357002935930651, 1.2548561676815113, -1.7222121494832052, -0.21466575368231167, 2.3706769588800585, 0.61173970698935742, -0.64252945513976001, -0.15975767627576784, -0.080476748010850724, -0.2641457675041311, -0.67346988308973754, 0.19913801658944555, -0.69409856461878749, -0.27934470605940293, -1.3000368703230192, -0.82817087051111538, -0.49589184943260473, 1.9159935053044717, 0.44277615140062349, -0.75657378430658695, 0.35609190579271255, -1.0788309660719575, -1.1514564984781768, 0.3327147536340227, -0.72702009605139595, 0.85874411311498267, 1.2190871794076124, -0.58769970503119662, -0.32503302314597859, -2.1805249569135103, -0.25889352863765258, 0.4221943219427422, -1.4161295098629991, -0.8223949237239897, 0.087269536066199027, 0.00091002222602847829, -0.29958992993204758, 0.22709481789571476, 1.4245467333996151, -1.0690042793374712, -0.82870740183752323, -1.0813022241229935, 0.095026594653833146, -1.8241990438452609, -0.63041662035239376, -0.27112408123801945, -1.8286639014447057, 3.1532215076313088, 0.94338416430945571, 1.2308918626084311, 1.0382715045172011, 0.58861656864129341, 0.36272327010100558, -0.20910807421322947, -0.2370308204975777, -0.89784503557366169, -1.3383856974948072, 0.2970592085010354, -1.0224949538906889, -0.10936189674880104, -0.35416233363429178, -1.1138659702239035, 0.080126266645301161, 0.42453609396564151, -0.35219820669963464, -0.62197437987430393, -0.055364060180076634, -0.48290098539659032, -0.35826842637430745, 1.2352426587257577, -0.007603082633630672, -0.32251007264504278, -0.33880012966966666, 0.071897449468532326, 0.55000716952022022, -0.1718386859829143, -0.83362000069023801, -1.1242201915687042, -0.010113418144405752, 0.46775984743407517, 0.95857421010704336, -0.78319773336451282, -0.69854582319017366, -1.7597754060130406, -0.7536087268436501, 1.6775791948789103, -0.84949187953488514, 1.614095615091885, -0.36677036495490523, -0.36363058788754854, 0.20065326225626889, 0.18220698786140455, 0.90885983588894292, 0.75497662509103258, 1.8096519261267159, -1.1670488472104956, -0.35035156360825481, 1.2292011485643548, 0.53111265030481658, 0.43399289079358716, 1.3626681250997539, 0.8607945721705027, -0.35793790154297156, 0.65938489743176143, -0.086132319692824852, 0.66382178846486573, -0.96013340453191587, 1.4263582523489349, -0.058807659154433291, 1.0112537495927754, 0.84759113404214648, -0.34169290908088557, -1.0408332560895484, 0.13522795609543886]</Parameters>
			</FullConnection>
			<FullConnection class="pybrain.structure.connections.full.FullConnection" name="hidden_to_out">
				<inmod val="hidden"/>
				<outmod val="out"/>
				<Parameters>[0.10250986447695934, 0.015940482663311009, 0.0084701377491742495, 0.0045824027700508306, 0.00042105600488964116, -0.028582851460621932, 0.052266961639274218, 0.12467480984753905]</Parameters>
			</FullConnection>
			<FullConnection class="pybrain.structure.connections.full.FullConnection" name="FullConnection-16" recurrent="True">
				<inmod val="hidden"/>
				<outmod val="context"/>
				<Parameters>[0.39303765593325185, 0.11680187742573911, 1.6814492690701373, -1.865556294862909, -0.12855858422881877, -0.42988430065655175, -1.5371171216781918, -0.53623817812299435, -2.2681577039797816, 1.1519419098189576, -1.9309474991500652, 0.64321530386168857, -1.1374512445440688, -0.42477574955053976, -0.79145296023346168, -1.5444494779904059, 0.31795880008382899, 0.98293678898277881, 1.4836922373435666, 0.94814693013728901, 1.8075086445207948, -1.8302459353923703, -2.7623517719807129, 1.5949510661423132, 0.48197917086332653, 0.47469163504289724, -0.24865616271378288, -0.40874981819940576, -0.89668617999892875, -0.527368923593735, -0.68640844762688347, -0.46201603853240586, 0.19127123247476985, 0.15816859819588289, 1.3435614819905644, 1.8277044894104191, 0.28385841114840143, 0.17167627672569238, -1.1679408012670156, 0.64639191774224336, 0.75017357431862575, 1.2690552960007073, -0.085966600215621705, -0.96269888229042022, 0.056704264850921511, -1.0419096959449856, -2.0440058891851911, -0.77565638749145716, -0.9324384186910174, -0.21379087880528685, -0.53349344765878437, 0.87443879026389615, 0.047123582950705366, -0.3627875103100604, 0.26274315145626015, -0.10539709331075563, -0.0090850769036314224, 1.4018284240287093, 0.2979880007828194, -1.9389236825791183, 0.83244045246484522, 0.058772935558457494, 0.71194555785736613, 1.942733404697776]</Parameters>
			</FullConnection>
		</Connections>
	</Network>
</PyBrain>
