<?xml version="1.0" ?>
<PyBrain>
	<Network class="pybrain.structure.networks.recurrent.RecurrentNetwork" name="RecurrentNetwork-275">
		<name val="'RecurrentNetwork-275'"/>
		<Modules>
			<LinearLayer class="pybrain.structure.modules.linearlayer.LinearLayer" inmodule="True" name="in">
				<dim val="30"/>
				<name val="'in'"/>
			</LinearLayer>
			<LinearLayer class="pybrain.structure.modules.linearlayer.LinearLayer" name="out" outmodule="True">
				<dim val="1"/>
				<name val="'out'"/>
			</LinearLayer>
			<LinearLayer class="pybrain.structure.modules.linearlayer.LinearLayer" name="context">
				<dim val="10"/>
				<name val="'context'"/>
			</LinearLayer>
			<TanhLayer class="pybrain.structure.modules.tanhlayer.TanhLayer" name="hidden">
				<dim val="10"/>
				<name val="'hidden'"/>
			</TanhLayer>
		</Modules>
		<Connections>
			<FullConnection class="pybrain.structure.connections.full.FullConnection" name="in_to_hidden">
				<inmod val="in"/>
				<outmod val="hidden"/>
				<Parameters>[-1.1225680727243146, -0.10987675768649253, 1.2237519202990583, 0.32888859671198095, 1.1335314129374239, -1.5421120677146574, 1.0687409676184694, -0.53852510786826691, 0.80614792963981741, 0.63966635920930426, -0.4544035368655559, -0.40832092489436506, -0.85130419393706558, -1.647743176151903, 0.020516390167216694, -0.64871269378928387, 0.32022190781170912, 1.0183773632713136, 0.2395508664937975, -0.79741112519701529, 0.35660841137930716, -1.9889479411842212, 1.5680253869775511, -0.36604846227809618, -0.92978936260755785, 0.58777260925699182, -0.61603532993176657, 0.07050670456087535, -0.10911297192289128, 0.46516571607608226, 0.65976600180956457, 2.0400002683266441, 0.15284175903216821, -0.305385989872481, 2.3715915585315845, -0.25954842723360133, 0.3668227338405009, 2.0573037221835366, 1.2918304963422582, -0.67330367540062275, -1.589332891404865, 1.3905998521882188, -2.6909676269396599, -0.92338557519324327, 0.20031119276039747, -0.47521749322935125, 0.41885708116830483, 0.22125836884832226, -2.7952146980411214, -0.14009219130379344, 0.047098732344927459, 0.46751919425361527, 1.2281982123683779, 0.24059502861335808, 0.46019251318567017, -1.2957092542081876, 2.6879849153541779, 0.78013111500390475, -0.688614196408871, -1.3880809416379363, -0.48666135423238666, -0.53474305815358059, 0.15548591098747908, 1.8460959338162444, -1.617051495085321, -0.97243242972294031, -0.42913751313448933, -0.62522229569550869, 0.85684224389725094, 0.55676138712447587, -0.63522319572646757, -0.47148531926335702, -0.14103498353387198, -0.76792057638936218, -0.34257392548614435, 1.9861852056483302, -2.0915582455167754, -1.3762119503490289, 1.9398315514149678, 1.0878465978906009, 0.57741111816537505, 1.1537509253443552, -1.0275103418218092, 0.519645804614431, 0.40417666511798606, -0.02871199586930745, -1.9909426277745526, 1.4566620256180622, -1.1141553757260783, -1.3936338159480581, -1.1034334541414568, -0.46506370937397778, -1.7298609863156909, -2.2898254175792481, -0.4042103340119661, -2.0035946807214136, 0.55117589560252123, -0.21599425834544972, 0.33439355288977174, -0.46493714674723563, 0.82602297744057451, 0.15191913820400679, 0.28631929465524858, -0.58147303909327863, 0.39322904013155163, -0.70043797840282807, 0.39245931348354418, 0.6335936614378801, 1.3033199375038358, -1.3471625546969654, -0.028305749451713012, -0.19789749440029469, 0.70061438199058235, -0.36425592360217812, -1.9299021740570756, 2.4801734725700149, -0.61595469445901108, -0.80305173129839647, -0.22963850141369585, -1.4615854261090671, 0.10066294429180501, 1.1257548427307229, 0.59680673536128115, -0.74037509291018333, 1.7157366114826105, -1.5011014628107806, -0.42176671786793518, -0.46813977027293019, 1.8573462437418142, 0.55863308625333152, -0.70637734185991441, 0.50390034802618378, -0.36284135586365235, -0.0023850757404863354, 1.6354747976933903, -1.5241660951141449, -1.155134189946329, -0.4721299192336903, 0.045408429686058918, -0.31167682717210698, -1.0940731328396236, 0.3075958867852619, -0.43256228703735905, 0.70516679520176306, 1.288808835488011, 0.32700051382351253, 0.8455074719762562, 0.53483195017401741, -1.5216776074540541, -0.010826699609058937, 0.26986162043956335, -0.25325871392792443, 0.93568544004815513, 0.064167459277497355, 0.93788482005808094, 1.2501610748667082, 0.59942682305578865, -1.3859100981025014, -0.87907547227858629, -1.997843934579655, 0.20415931446527852, -1.0772580893318089, 0.27914940289928963, -0.52073930032625204, 0.56013689317424675, -0.56892945592681554, 0.61129389328945971, 1.2662524939398234, -0.55939485446037374, 0.65600616100571796, 0.34438709246739657, 0.5730470955093474, -0.45678396046645708, -1.3157375871391339, -1.5151311975128645, 0.38908706479127436, -0.059435079396480565, -1.2767906427509177, -0.36918433159034869, -0.23884015708423387, -1.2110570820096136, 1.073368241068307, -0.66187840300306899, -2.543641827175696, 0.52003045482910182, -0.28094393346313573, -1.3343890115677122, -0.3826615693781385, 0.45950300811332301, 0.75204588731285349, -0.38588940529140198, 1.0689798364096097, 0.88845526447973677, -0.76377040435015819, -0.1254127704969806, -0.32564731439200434, -1.013760820532587, 1.4250890578931603, -1.1040426696831056, 2.4058975367748965, 1.1686480487176771, -0.29994496903588036, 0.61419272143872738, -0.54215176335956805, 1.0449150072072433, 0.3518368421427977, 0.10593208448884252, 1.2860472711760902, -0.033539760765825419, -0.4702537514194593, -0.6531777982164616, -0.94494842550390001, -0.58267636937429124, 0.11588561957031335, 0.46913305139031714, 1.3744599534587973, -0.85849235042847194, -0.24203304216838301, -0.36993657629549054, 0.85881608259802644, 0.92245828612141434, 1.5968589668006068, 0.48143439954454881, -0.50411436787231312, -0.31440547353357018, 0.14079107726127799, 0.44834536184532947, -0.84572952811875368, 1.6619669716007628, 0.24418614572200539, 1.496344654972616, 0.19921019671471252, -0.29223708044264257, -0.87730830448825003, -1.1640800590423681, -1.1076502791255065, -1.0595896718147106, 0.11890614537174468, -1.5421485637171617, -1.1757681783804552, -1.337904183758758, -0.095682853660444184, 2.2514723118535773, 0.55552042654890876, 0.94821267838792023, 1.4754117997338914, -0.67230522384609459, -2.0649925864961802, 0.41531911897547863, -0.13760170620190657, 1.4185455652423109, -0.91248275439943161, 0.46638019408379577, -1.2873619381790165, -1.6868608914453682, 0.87678373286409927, 2.153145995984568, 1.5087877385178021, 0.83014537503587393, 0.20220410764035585, -0.46973157428849116, -0.01232649695357118, -0.50986605202182433, 0.71778581222569282, -0.83365949443365306, 0.054414391882314311, 1.6541404446736436, -0.23031521251918927, 0.58421662002872399, -0.36632557563292717, -0.67584021984471976, -0.70012117401973928, 0.25132682598225442, 1.416870577456218, -0.5770021861131539, 0.25439066926434184, -0.92726260230324575, 2.1652742306997896, -0.27285992108398927, 0.041847501994645625, 0.44313594170326687, -1.1033807472641632, 0.40864382957287632, -0.13744103583423134, -0.23052133592108073, -0.24897735144809238, 0.28702521336585701, -0.18261007643886398, -1.6740234797263183, 0.3086428445766044, -1.6175653629293476, -1.0375643520088706, 0.13794102512299508, 0.46888146401423342, 0.84862934032342008, -1.0540344420669641, 0.79980739461093997, -0.49382483024956036, -0.12547842890997221, 0.56103902472998168]</Parameters>
			</FullConnection>
			<FullConnection class="pybrain.structure.connections.full.FullConnection" name="hidden_to_out">
				<inmod val="hidden"/>
				<outmod val="out"/>
				<Parameters>[0.15474676083464672, -0.12490401012665557, -0.084182843531028839, -0.24634131582539065, 0.026790970954754176, 0.036323431854911784, 0.11993575579116542, -0.01315966770542653, -0.091789353165787915, 0.020724997163191178]</Parameters>
			</FullConnection>
			<FullConnection class="pybrain.structure.connections.full.FullConnection" name="FullConnection-274" recurrent="True">
				<inmod val="hidden"/>
				<outmod val="context"/>
				<Parameters>[0.31012716702525794, -0.6884044036167678, -0.52214644616418915, -0.13849362721698277, -0.60356954937767859, 1.0770685734129302, 0.043251600228274949, 0.31129511046458319, 0.96664351918823865, 1.0465311364530847, 1.0774908702810162, 0.78995384184524298, -1.0341831497411484, -0.70238009150633007, -0.14609855046060613, -0.29198074467993423, 0.86201679505217133, -0.32524907433624084, 1.2659726454855385, 0.86232180409840165, -0.70368370586917406, -2.3474484781464149, -0.050122291662951422, -0.8894698068053476, -0.75412004879859706, -0.7294728521465691, -0.61934113675721714, -0.31290025195291188, 1.5273268732411303, 0.24584740713532624, 2.2620680478160926, -0.34780334662245666, 2.3827674427845902, -0.37326670750001639, 1.9698423158885348, -1.0822785605640535, 1.5467784657652026, -0.4757688462000611, -1.238212015455503, 2.5042825861221036, 1.224357916455336, -0.42848167768152007, 1.0754593358480464, -0.22865444217705552, -0.8637989146989673, -1.3659959975206515, -0.50394292912976502, -0.24984385883735374, -1.1424515294498701, 1.343370010362368, 0.99459862598448423, 0.90297539946736527, -0.044817763173787981, -0.23092712387198194, 0.31668018982068413, 1.5596769666963799, -0.45076491280630593, -0.10157576555348624, -0.54247942944139127, -0.32352425291794185, 0.54414450378637247, -0.74094701831895948, 0.18812850124017388, -1.028945262641997, -0.96590104295229418, -0.52725702127094531, -0.28310710304210723, 0.60736480647930635, -1.1010570962698993, 0.50080466424039538, 0.30098053532620966, -0.6202273405469434, -1.2634588010668311, -2.3396323731849225, -0.34763452704966569, 0.47122750634526667, 0.28789523449346366, 0.99873690373244983, -1.2350392719055463, -0.2212331305147906, -0.78675206935103192, 0.095757434382424497, 1.2189144807691756, 0.50931169833415135, -1.5621684748301439, -0.20448450767097431, 0.30373887890041629, 0.33986490009510983, 0.320143863224366, -0.13631268312931216, -0.61000098436306227, 0.028055904201205292, 1.3695045337031611, 0.49195881367372563, -1.5927139849515728, 0.7711191553088671, 0.99411268521384966, 0.84671785925645648, 1.4079829216120392, 1.2021340088659502]</Parameters>
			</FullConnection>
		</Connections>
	</Network>
</PyBrain>
